README.rst
setup.py
arguments/__init__.py
arguments.egg-info/PKG-INFO
arguments.egg-info/SOURCES.txt
arguments.egg-info/dependency_links.txt
arguments.egg-info/top_level.txt
arguments.egg-info/zip-safe
fallbackdocopt/__init__.py