Metadata-Version: 1.1
Name: arguments
Version: 76
Summary: Argument parser based on docopt
Home-page: https://github.com/erikdejonge/arguments
Author: Erik de Jonge
Author-email: erik@a8.nl
License: GPL
Platform: UNKNOWN
Classifier: Programming Language :: Python
Classifier: Programming Language :: Python :: 3
Classifier: Intended Audience :: Developers
Classifier: License :: OSI Approved :: GNU Library or Lesser General Public License (LGPL)
Classifier: Operating System :: POSIX
Classifier: Topic :: Software Development :: Libraries :: Python Modules
Classifier: Topic :: System
Requires: future
Requires: ujson
Requires: sh
